{
  "_format": "hh-sol-cache-2",
  "files": {
    "C:\\Users\\sande\\OneDrive\\Desktop\\DecentraHost\\contracts\\Lock.sol": {
      "lastModificationDate": 1732383735918,
      "contentHash": "1da7c271214aff7ac25799dbcbca36be",
      "sourceName": "contracts/Lock.sol",
      "solcConfig": {
        "version": "0.8.27",
        "settings": {
          "evmVersion": "paris",
          "optimizer": {
            "enabled": false,
            "runs": 200
          },
          "outputSelection": {
            "*": {
              "*": [
                "abi",
                "evm.bytecode",
                "evm.deployedBytecode",
                "evm.methodIdentifiers",
                "metadata"
              ],
              "": [
                "ast"
              ]
            }
          }
        }
      },
      "imports": [],
      "versionPragmas": [
        "^0.8.27"
      ],
      "artifacts": [
        "Lock"
      ]
    },
    "C:\\Users\\sande\\OneDrive\\Desktop\\DecentraHost\\contracts\\WebpagesStorage.sol": {
      "lastModificationDate": 1732385981376,
      "contentHash": "1f0e23546fceed9ab526cd48707c32b2",
      "sourceName": "contracts/WebpagesStorage.sol",
      "solcConfig": {
        "version": "0.8.27",
        "settings": {
          "evmVersion": "paris",
          "optimizer": {
            "enabled": false,
            "runs": 200
          },
          "outputSelection": {
            "*": {
              "*": [
                "abi",
                "evm.bytecode",
                "evm.deployedBytecode",
                "evm.methodIdentifiers",
                "metadata"
              ],
              "": [
                "ast"
              ]
            }
          }
        }
      },
      "imports": [],
      "versionPragmas": [
        "^0.8.27"
      ],
      "artifacts": [
        "WebpageStorage"
      ]
    }
  }
}
